regref/__init__.py
regref/main.py
regref/version.py
regref-2.1.1.dist-info/LICENSE
regref-2.1.1.dist-info/METADATA
regref-2.1.1.dist-info/WHEEL
regref-2.1.1.dist-info/entry_points.txt
regref-2.1.1.dist-info/top_level.txt
regref-2.1.1.dist-info/RECORD
