Metadata-Version: 2.1
Name: regref
Version: 2.1.1
Summary: Munge tables of data
Home-page: https://github.com/arendsee/regref
Author: Zebulun Arendsee
Author-email: zbwrnz@gmail.com
License: UNKNOWN
Platform: UNKNOWN
Classifier: Programming Language :: Python :: 3
Classifier: License :: OSI Approved :: MIT License
Classifier: Operating System :: OS Independent
